README.md
setup.py
openf5_utils/__init__.py
openf5_utils/ipa.py
openf5_utils.egg-info/PKG-INFO
openf5_utils.egg-info/SOURCES.txt
openf5_utils.egg-info/dependency_links.txt
openf5_utils.egg-info/requires.txt
openf5_utils.egg-info/top_level.txt
openf5_utils/data/__init__.py
openf5_utils/data/prepare_emilia_v2.py